{
    "name": "akk-alert",
    "scope": [
        {
            "title": "@",
            "message": "@",
            "icon": "@",
            "event": "@",
            "type": "@",
            "isDisplayed": "=",
            "isClosable": "="
        }
    ],
    "title": "Youpi",
    "message": "Il va faire beau !",
    "icon": "warning",
    "types": "{{view.alert.model}}",
    "isDisplayed": "view.alert.isDisplayed",
    "isClosable": "view.alert.isClosable",
    "description": "The akk-select tag here is used to change the type of the alert so you can see the diffrent options it has to offer, another example it's of usage is available below."
}
