{
    "name": "akk-checkbox",
    "scope": [
        {
            "label": "@",
            "alignment": "@",
            "elementclass": "@",
            "req": "@",
            "model": "=",
            "property": "@",
            "eventUpdate": "@"
        }
    ],
    "label": "Do accept the conditions of use (there a none anyway) ?",
    "alignment": "",
    "elementclass": "",
    "req": "",
    "model": "view",
    "property": "acceptanceValue",
    "description": "Here we have our akk-checkbox directive, it takes three values, the label, the model object and the property to take from that model object. The property will contain true if akk-checkbox is checked, or false."
}
